README.md
setup.py
spider_common/__init__.py
spider_common.egg-info/PKG-INFO
spider_common.egg-info/SOURCES.txt
spider_common.egg-info/dependency_links.txt
spider_common.egg-info/requires.txt
spider_common.egg-info/top_level.txt
spider_common.egg-info/zip-safe
spider_common/clue/__init__.py
spider_common/clue/api.py
spider_common/clue/constants.py
spider_common/clue/models.py
spider_common/clue/scrapy/__init__.py
spider_common/clue/scrapy/extensions.py
spider_common/clue/scrapy/items.py
spider_common/clue/scrapy/middlewares.py
spider_common/clue/scrapy/pipelines.py
spider_common/clue/scrapy/spider.py
spider_common/common_utils/__init__.py
spider_common/common_utils/exceptions.py
spider_common/common_utils/time.py
spider_common/notify/__init__.py
spider_common/notify/constants/__init__.py
spider_common/notify/constants/signals.py
spider_common/notify/scrapy/__init__.py
spider_common/notify/scrapy/extensions/__init__.py
spider_common/notify/scrapy/extensions/signal_handler.py
spider_common/persistent/__init__.py
spider_common/persistent/items/__init__.py
spider_common/persistent/items/base.py
spider_common/persistent/items/shop.py
spider_common/persistent/scrapy/__init__.py
spider_common/persistent/scrapy/dw_logger.py
spider_common/persistent/scrapy/pipelines/__init__.py
spider_common/persistent/scrapy/pipelines/dw_pipeline.py
spider_common/persistent/scrapy/pipelines/mysql_pipeline.py